torch_pdegraph/__init__.py
torch_pdegraph/utilities.py
torch_pdegraph/operators/GradInfNorm.py
torch_pdegraph/operators/GradMinusInfNorm.py
torch_pdegraph/operators/GradMinusNorm.py
torch_pdegraph/operators/GradNorm.py
torch_pdegraph/operators/GradPlusInfNorm.py
torch_pdegraph/operators/GradPlusNorm.py
torch_pdegraph/operators/LapAniso.py
torch_pdegraph/operators/LapIso.py
torch_pdegraph/operators/MeanCurv.py
torch_pdegraph/operators/__init__.py
torch_pdegraph/pdes/__init__.py
torch_pdegraph/pdes/pdeanisodiff.py
torch_pdegraph/pdes/pdeinflapdiff.py
torch_pdegraph/pdes/pdeisodiff.py
torch_pdegraph/pdes/pdemorphdilation.py
torch_pdegraph/pdes/pdemorpherosion.py
torch_pdegraph-1.1.2.dist-info/LICENSE
torch_pdegraph-1.1.2.dist-info/METADATA
torch_pdegraph-1.1.2.dist-info/WHEEL
torch_pdegraph-1.1.2.dist-info/top_level.txt
torch_pdegraph-1.1.2.dist-info/RECORD
