Metadata-Version: 2.1
Name: torch-pdegraph
Version: 1.1.2
Summary: Running paritial difference equations (PDEs) on graphs
Home-page: https://github.com/aGIToz/Pytorch_pdegraph
Author: Amitoz AZAD
Author-email: amitoz.sudo@gmail.com
License: MIT
Platform: UNKNOWN
Requires-Python: >=3.6
Requires-Dist: matplotlib
Requires-Dist: mnist
Requires-Dist: numpy
Requires-Dist: open3d-python
Requires-Dist: scikit-image
Requires-Dist: scikit-learn
Requires-Dist: torch
Requires-Dist: tqdm
